auto_py_to_exe/__init__.py
auto_py_to_exe/__main__.py
auto_py_to_exe/config.py
auto_py_to_exe/dialogs.py
auto_py_to_exe/packaging.py
auto_py_to_exe/ui.py
auto_py_to_exe/utils.py
auto_py_to_exe/validation.py
auto_py_to_exe/web/Nunito-Light.ttf
auto_py_to_exe/web/favicon.ico
auto_py_to_exe/web/index.html
auto_py_to_exe/web/css/general.css
auto_py_to_exe/web/css/main.css
auto_py_to_exe/web/css/modal.css
auto_py_to_exe/web/img/chevron-square-up.svg
auto_py_to_exe/web/img/plus.svg
auto_py_to_exe/web/img/remove.svg
auto_py_to_exe/web/js/configuration.js
auto_py_to_exe/web/js/constants.js
auto_py_to_exe/web/js/i18n.js
auto_py_to_exe/web/js/importExport.js
auto_py_to_exe/web/js/initialise.js
auto_py_to_exe/web/js/interface.js
auto_py_to_exe/web/js/messages.js
auto_py_to_exe/web/js/modal.js
auto_py_to_exe/web/js/packaging.js
auto_py_to_exe/web/js/staticEvents.js
auto_py_to_exe/web/js/utils.js
qiqiqi-2.18.1.dist-info/LICENSE
qiqiqi-2.18.1.dist-info/METADATA
qiqiqi-2.18.1.dist-info/WHEEL
qiqiqi-2.18.1.dist-info/entry_points.txt
qiqiqi-2.18.1.dist-info/top_level.txt
qiqiqi-2.18.1.dist-info/RECORD
