Metadata-Version: 2.1
Name: qiqiqi
Version: 2.18.1
Summary: Converts .py to .exe using a simple graphical interface.
Home-page: https://github.com/haoqi7/auto-py-exe
Author: haoqi
Author-email: w00989988@gmail.com
License: MIT
Keywords: gui,executable
Platform: UNKNOWN
Classifier: License :: OSI Approved :: MIT License
Classifier: Programming Language :: Python
Classifier: Programming Language :: Python :: 3
Classifier: Programming Language :: Python :: 3.6
Classifier: Programming Language :: Python :: 3.7
Classifier: Programming Language :: Python :: 3.8
Classifier: Programming Language :: Python :: 3.9
Classifier: Programming Language :: Python :: 3.10
Classifier: Operating System :: Microsoft :: Windows
Classifier: Operating System :: POSIX :: Linux
Requires-Python: >=3.6
Requires-Dist: Eel (==0.12.4)
Requires-Dist: pyinstaller (>=4.6)
